selphyprint/__init__.py
selphyprint/main.py
selphyprint/printing.py
selphyprint-0.0.5.dist-info/LICENSE
selphyprint-0.0.5.dist-info/METADATA
selphyprint-0.0.5.dist-info/WHEEL
selphyprint-0.0.5.dist-info/entry_points.txt
selphyprint-0.0.5.dist-info/top_level.txt
selphyprint-0.0.5.dist-info/RECORD
