Metadata-Version: 2.2
Name: selphyprint
Version: 0.0.5
Summary: Prepare an image for printing on Canon Selphy printers without cropping
Author-email: Roman <roman@kosobrodov.net>
Project-URL: Homepage, https://github.com/RomanKosobrodov/selphy-print
Project-URL: Bug Tracker, https://github.com/RomanKosobrodov/selphy-print
Keywords: Canon Selphy crop bleeding
Classifier: Programming Language :: Python :: 3
Classifier: License :: OSI Approved :: GNU General Public License v3 (GPLv3)
Classifier: Operating System :: OS Independent
Requires-Python: >=3.7
License-File: LICENSE
Requires-Dist: pillow>=10.3.0
